pyLoraRFM9x/__init__.py
pyLoraRFM9x/constants.py
pyLoraRFM9x/lora.py
pyLoraRFM9x-1.0.1.dist-info/LICENSE
pyLoraRFM9x-1.0.1.dist-info/METADATA
pyLoraRFM9x-1.0.1.dist-info/WHEEL
pyLoraRFM9x-1.0.1.dist-info/top_level.txt
pyLoraRFM9x-1.0.1.dist-info/RECORD
