Metadata-Version: 2.1
Name: pyLoraRFM9x
Version: 1.0.1
Summary: Interrupt driven LoRa RFM9x library for Raspberry Pi inspired by RadioHead
Author-email: Edwin Peters <edwin.g.w.peters@gmail.com>
License: MIT License
Project-URL: Homepage, https://github.com/epeters13/pyLoraRFM9x
Project-URL: Issues, https://github.com/epeters13/pyLoraRFM9x/issues
Keywords: lora,rfm95,rfm9x,rfm96,rfm97,rfm98,hardware,raspberrypi
Classifier: Development Status :: 4 - Beta
Classifier: Programming Language :: Python :: 3
Classifier: License :: OSI Approved :: MIT License
Classifier: Intended Audience :: Developers
Classifier: Topic :: Software Development :: Libraries
Classifier: Topic :: System :: Hardware
Requires-Python: >=3.5
License-File: LICENSE
Requires-Dist: lgpio
Requires-Dist: spidev
